LICENSE
tryceratops/__init__.py
tryceratops/__main__.py
tryceratops/analyzers/__init__.py
tryceratops/analyzers/base.py
tryceratops/analyzers/call.py
tryceratops/analyzers/classdefs.py
tryceratops/analyzers/conditional.py
tryceratops/analyzers/exception_block.py
tryceratops/analyzers/exceptions.py
tryceratops/analyzers/try_block.py
tryceratops/files/__init__.py
tryceratops/files/discovery.py
tryceratops/files/parser.py
tryceratops/fixers/__init__.py
tryceratops/fixers/base.py
tryceratops/fixers/exception_block.py
tryceratops/fixers/exceptions.py
tryceratops/flake_plugin.py
tryceratops/interfaces.py
tryceratops/logging_config.py
tryceratops/parsing_types.py
tryceratops/processors.py
tryceratops/runners.py
tryceratops/settings.py
tryceratops/violations/__init__.py
tryceratops/violations/codes.py
tryceratops/violations/violations.py
tryceratops-2.4.1.dist-info/LICENSE
tryceratops-2.4.1.dist-info/METADATA
tryceratops-2.4.1.dist-info/WHEEL
tryceratops-2.4.1.dist-info/entry_points.txt
tryceratops-2.4.1.dist-info/RECORD
