Metadata-Version: 2.1
Name: tryceratops
Version: 2.4.1
Summary: Prevent Exception Handling AntiPatterns
Home-page: https://github.com/guilatrova/tryceratops
License: MIT
Keywords: lint,try,except
Author: Guilherme Latrova
Author-email: hello@guilatrova.dev
Requires-Python: >=3.8.1,<4.0
Classifier: Development Status :: 4 - Beta
Classifier: Environment :: Console
Classifier: Intended Audience :: Developers
Classifier: License :: OSI Approved :: MIT License
Classifier: Operating System :: OS Independent
Classifier: Programming Language :: Python :: 3
Classifier: Programming Language :: Python :: 3.9
Classifier: Programming Language :: Python :: 3.10
Classifier: Programming Language :: Python :: 3.11
Classifier: Programming Language :: Python :: 3.12
Classifier: Programming Language :: Python :: 3.13
Classifier: Topic :: Software Development :: Libraries :: Python Modules
Classifier: Topic :: Software Development :: Quality Assurance
Requires-Dist: click (>=7)
Requires-Dist: rich (>=10.14.0)
Requires-Dist: tomli (>=2.0.1,<3.0.0) ; python_version < "3.11"
Requires-Dist: typing-extensions (>=4.5.0) ; python_version < "3.11"
Project-URL: Changelog, https://github.com/guilatrova/tryceratops/blob/main/CHANGELOG.md
Project-URL: Repository, https://github.com/guilatrova/tryceratops
